{
  "AWSTemplateFormatVersion": "2010-09-09",
  "Transform": "AWS::Serverless-2016-10-31",
  "Outputs": {
    "RestAPIId": {
      "Value": {
        "Ref": "RestAPI"
      }
    },
    "APIHandlerName": {
      "Value": {
        "Ref": "APIHandler"
      }
    },
    "APIHandlerArn": {
      "Value": {
        "Fn::GetAtt": [
          "APIHandler",
          "Arn"
        ]
      }
    },
    "EndpointURL": {
      "Value": {
        "Fn::Sub": "https://${RestAPI}.execute-api.${AWS::Region}.${AWS::URLSuffix}/api/"
      }
    }
  },
  "Resources": {
    "DefaultRole": {
      "Type": "AWS::IAM::Role",
      "Properties": {
        "AssumeRolePolicyDocument": {
          "Version": "2012-10-17",
          "Statement": [
            {
              "Sid": "",
              "Effect": "Allow",
              "Principal": {
                "Service": "lambda.amazonaws.com"
              },
              "Action": "sts:AssumeRole"
            }
          ]
        },
        "Policies": [
          {
            "PolicyDocument": {
              "Version": "2012-10-17",
              "Statement": [
                {
                  "Effect": "Allow",
                  "Action": [
                    "iot:DescribeCertificate",
                    "iot:DescribeThing",
                    "iot:ListPrincipalThings",
                    "iot:RegisterThing"
                  ],
                  "Resource": [
                    "*"
                  ],
                  "Sid": "831c65acaf2a4255a635efcc2332d79b"
                },
                {
                  "Effect": "Allow",
                  "Action": [
                    "logs:CreateLogGroup",
                    "logs:CreateLogStream",
                    "logs:PutLogEvents"
                  ],
                  "Resource": "arn:*:logs:*:*:*"
                }
              ]
            },
            "PolicyName": "DefaultRolePolicy"
          }
        ]
      }
    },
    "RestAPI": {
      "Type": "AWS::Serverless::Api",
      "Properties": {
        "EndpointConfiguration": "EDGE",
        "StageName": "api",
        "DefinitionBody": {
          "swagger": "2.0",
          "info": {
            "version": "1.0",
            "title": "device-registration-api"
          },
          "schemes": [
            "https"
          ],
          "paths": {
            "/token": {
              "get": {
                "consumes": [
                  "application/json"
                ],
                "produces": [
                  "application/json"
                ],
                "responses": {
                  "200": {
                    "description": "200 response",
                    "schema": {
                      "$ref": "#/definitions/Empty"
                    }
                  }
                },
                "x-amazon-apigateway-integration": {
                  "responses": {
                    "default": {
                      "statusCode": "200"
                    }
                  },
                  "uri": {
                    "Fn::Sub": "arn:${AWS::Partition}:apigateway:${AWS::Region}:lambda:path/2015-03-31/functions/${APIHandler.Arn}/invocations"
                  },
                  "passthroughBehavior": "when_no_match",
                  "httpMethod": "POST",
                  "contentHandling": "CONVERT_TO_TEXT",
                  "type": "aws_proxy"
                }
              }
            },
            "/certificate": {
              "post": {
                "consumes": [
                  "application/json"
                ],
                "produces": [
                  "application/json"
                ],
                "responses": {
                  "200": {
                    "description": "200 response",
                    "schema": {
                      "$ref": "#/definitions/Empty"
                    }
                  }
                },
                "x-amazon-apigateway-integration": {
                  "responses": {
                    "default": {
                      "statusCode": "200"
                    }
                  },
                  "uri": {
                    "Fn::Sub": "arn:${AWS::Partition}:apigateway:${AWS::Region}:lambda:path/2015-03-31/functions/${APIHandler.Arn}/invocations"
                  },
                  "passthroughBehavior": "when_no_match",
                  "httpMethod": "POST",
                  "contentHandling": "CONVERT_TO_TEXT",
                  "type": "aws_proxy"
                }
              }
            },
            "/upload": {
              "post": {
                "consumes": [
                  "application/json"
                ],
                "produces": [
                  "application/json"
                ],
                "responses": {
                  "200": {
                    "description": "200 response",
                    "schema": {
                      "$ref": "#/definitions/Empty"
                    }
                  }
                },
                "x-amazon-apigateway-integration": {
                  "responses": {
                    "default": {
                      "statusCode": "200"
                    }
                  },
                  "uri": {
                    "Fn::Sub": "arn:${AWS::Partition}:apigateway:${AWS::Region}:lambda:path/2015-03-31/functions/${APIHandler.Arn}/invocations"
                  },
                  "passthroughBehavior": "when_no_match",
                  "httpMethod": "POST",
                  "contentHandling": "CONVERT_TO_TEXT",
                  "type": "aws_proxy"
                },
                "security": [
                  {
                    "sigv4": []
                  }
                ]
              }
            }
          },
          "definitions": {
            "Empty": {
              "type": "object",
              "title": "Empty Schema"
            }
          },
          "x-amazon-apigateway-binary-media-types": [
            "application/octet-stream",
            "application/x-tar",
            "application/zip",
            "audio/basic",
            "audio/ogg",
            "audio/mp4",
            "audio/mpeg",
            "audio/wav",
            "audio/webm",
            "image/png",
            "image/jpg",
            "image/jpeg",
            "image/gif",
            "video/ogg",
            "video/mpeg",
            "video/webm"
          ],
          "securityDefinitions": {
            "sigv4": {
              "in": "header",
              "type": "apiKey",
              "name": "Authorization",
              "x-amazon-apigateway-authtype": "awsSigv4"
            }
          }
        }
      }
    },
    "APIHandler": {
      "Type": "AWS::Serverless::Function",
      "Properties": {
        "Runtime": "python3.8",
        "Handler": "app.app",
        "CodeUri": {
          "Bucket": "${Token[TOKEN.85]}",
          "Key": "${Token[TOKEN.88]}${Token[TOKEN.90]}"
        },
        "Tags": {
          "aws-chalice": "version=1.22.4:stage=device-registration-api:app=device-registration-api"
        },
        "Tracing": "PassThrough",
        "Timeout": 60,
        "MemorySize": 128,
        "Role": {
          "Fn::GetAtt": [
            "DefaultRole",
            "Arn"
          ]
        }
      }
    },
    "APIHandlerInvokePermission": {
      "Type": "AWS::Lambda::Permission",
      "Properties": {
        "FunctionName": {
          "Ref": "APIHandler"
        },
        "Action": "lambda:InvokeFunction",
        "Principal": "apigateway.amazonaws.com",
        "SourceArn": {
          "Fn::Sub": [
            "arn:${AWS::Partition}:execute-api:${AWS::Region}:${AWS::AccountId}:${RestAPIId}/*",
            {
              "RestAPIId": {
                "Ref": "RestAPI"
              }
            }
          ]
        }
      }
    }
  }
}